yapi/__init__.py
yapi/args.py
yapi/extensions.py
yapi/loader.py
yapi/main.py
yapi/request.py
yapi/response.py
yapi/utils.py
yapi_ci-0.1.7.data/scripts/yapi
yapi_ci-0.1.7.dist-info/LICENSE
yapi_ci-0.1.7.dist-info/METADATA
yapi_ci-0.1.7.dist-info/WHEEL
yapi_ci-0.1.7.dist-info/top_level.txt
yapi_ci-0.1.7.dist-info/RECORD
