Metadata-Version: 2.1
Name: yapi-ci
Version: 0.1.7
Summary: Using yaml to talk to APIs in an automated, descriptive way.
Home-page: https://github.com/bruj0/yapi
Author: Rodrigo Diaz Leven
Author-email: ramakandra@gmail.com
License: MIT
Platform: UNKNOWN
Classifier: Programming Language :: Python :: 3
Classifier: License :: OSI Approved :: MIT License
Classifier: Operating System :: OS Independent
Requires-Python: >=3.6
Requires-Dist: certifi (>=2019.9.11)
Requires-Dist: chardet (>=3.0.4)
Requires-Dist: flatten-json (>=0.1.7)
Requires-Dist: idna (>=2.8)
Requires-Dist: python-box (>=3.4.5)
Requires-Dist: PyYAML (>=5.1.2)
Requires-Dist: requests (>=2.22.0)
Requires-Dist: requests-toolbelt (>=0.9.1)
Requires-Dist: six (>=1.13.0)
Requires-Dist: urllib3 (>=1.25.6)
